[
  {
    "colors": "red.200",
    "info": [
      { "option": "동혜담" },
      { "option": "유 빈" },
      { "option": "고민지" },
      { "option": "조윤서" },
      { "option": "황종수" },
      { "option": "이예주" },
      { "option": "지 율" },
      { "option": "오주은" },
      { "option": "유지원" },
      { "option": "이명제" },
      { "option": "이세인" },
      { "option": "이규리" },
      { "option": "최 선" },
      { "option": "양선혜" },
      { "option": "이건송" },
      { "option": "윤서린" },
      { "option": "허주연" },
      { "option": "이운우" },
      { "option": "이세영" },
      { "option": "김다은" },
      { "option": "김도현" }
    ]
  },
  {
    "colors": "purple.200",
    "info": [
      { "option": "고민지" },
      { "option": "오주은" },
      { "option": "유지원" },
      { "option": "유 빈" },
      { "option": "이세인" },
      { "option": "동혜담" },
      { "option": "이세영" },
      { "option": "이호연" },
      { "option": "박새미" },
      { "option": "윤서준" },
      { "option": "성수호" },
      { "option": "지 율" },
      { "option": "김다은" },
      { "option": "윤서린" },
      { "option": "조윤서" },
      { "option": "이건송" },
      { "option": "이예주" },
      { "option": "이규리" },
      { "option": "김민주" },
      { "option": "황종수" },
      { "option": "이운우" },
      { "option": "정하윤" },
      { "option": "최수민" },
      { "option": "김도현" }
    ]
  },
  {
    "colors": "orange.200",
    "info": [
      { "option": "김다은" },
      { "option": "이건송" },
      { "option": "최 선" },
      { "option": "이규리" },
      { "option": "이세영" },
      { "option": "유 빈" },
      { "option": "이예주" },
      { "option": "지 율" },
      { "option": "허주연" },
      { "option": "오주은" },
      { "option": "이호연" },
      { "option": "동혜담" },
      { "option": "박새미" },
      { "option": "이명제" },
      { "option": "이세인" },
      { "option": "이운우" },
      { "option": "김민주" },
      { "option": "고민지" },
      { "option": "성수호" },
      { "option": "유지원" },
      { "option": "전윤민" }
    ]
  },
  {
    "colors": "green.200",
    "info": [
      { "option": "이호연" },
      { "option": "양선혜" },
      { "option": "이건송" },
      { "option": "최수민" },
      { "option": "최 선" },
      { "option": "이예주" },
      { "option": "조윤서" },
      { "option": "동혜담" },
      { "option": "지 율" },
      { "option": "황종수" },
      { "option": "이운우" },
      { "option": "이세영" },
      { "option": "오주은" },
      { "option": "윤서준" },
      { "option": "정하윤" },
      { "option": "이명제" },
      { "option": "이세인" },
      { "option": "김다은" },
      { "option": "유 빈" },
      { "option": "김민주" },
      { "option": "박새미" },
      { "option": "고민지" },
      { "option": "전예은" },
      { "option": "이규리" },
      { "option": "유지원" },
      { "option": "전윤민" }
    ]
  },
  {
    "colors": "yellow.200",
    "info": [
      { "option": "이세인" },
      { "option": "김다은" },
      { "option": "고민지" },
      { "option": "유지원" },
      { "option": "오주은" },
      { "option": "이세영" },
      { "option": "동혜담" },
      { "option": "이규리" },
      { "option": "이건송" },
      { "option": "유 빈" },
      { "option": "지 율" },
      { "option": "이운우" },
      { "option": "이예주" }
    ]
  }
]
